README.md
setup.py
fulcrum/__init__.py
fulcrum/exceptions.py
fulcrum/mixins.py
fulcrum/utils.py
fulcrum.egg-info/PKG-INFO
fulcrum.egg-info/SOURCES.txt
fulcrum.egg-info/dependency_links.txt
fulcrum.egg-info/requires.txt
fulcrum.egg-info/top_level.txt
fulcrum/api/__init__.py
fulcrum/api/endpoints.py