Metadata-Version: 1.0
Name: fulcrum
Version: 1.11.0
Summary: A python wrapper for the Fulcrum API
Home-page: https://github.com/fulcrumapp/fulcrum-python
Author: Jason Sanford
Author-email: jasonsanford@gmail.com
License: Apache License
Platform: UNKNOWN
